cats_img_cls_helper/__init__.py
cats_img_cls_helper/_nbdev.py
cats_img_cls_helper/core.py
cats_img_cls_helper-0.0.1.dist-info/LICENSE
cats_img_cls_helper-0.0.1.dist-info/METADATA
cats_img_cls_helper-0.0.1.dist-info/WHEEL
cats_img_cls_helper-0.0.1.dist-info/entry_points.txt
cats_img_cls_helper-0.0.1.dist-info/top_level.txt
cats_img_cls_helper-0.0.1.dist-info/RECORD
